opensesame_plugins/titta/__init__.py
opensesame_plugins/titta/titta_calibrate/__init__.py
opensesame_plugins/titta/titta_calibrate/titta_calibrate.png
opensesame_plugins/titta/titta_calibrate/titta_calibrate.py
opensesame_plugins/titta/titta_calibrate/titta_calibrate_large.png
opensesame_plugins/titta/titta_init/__init__.py
opensesame_plugins/titta/titta_init/titta_init.png
opensesame_plugins/titta/titta_init/titta_init.py
opensesame_plugins/titta/titta_init/titta_init_large.png
opensesame_plugins/titta/titta_plot_gaze/__init__.py
opensesame_plugins/titta/titta_plot_gaze/titta_plot_gaze.png
opensesame_plugins/titta/titta_plot_gaze/titta_plot_gaze.py
opensesame_plugins/titta/titta_plot_gaze/titta_plot_gaze_large.png
opensesame_plugins/titta/titta_save_data/__init__.py
opensesame_plugins/titta/titta_save_data/titta_save_data.png
opensesame_plugins/titta/titta_save_data/titta_save_data.py
opensesame_plugins/titta/titta_save_data/titta_save_data_large.png
opensesame_plugins/titta/titta_send_message/__init__.py
opensesame_plugins/titta/titta_send_message/titta_send_message.png
opensesame_plugins/titta/titta_send_message/titta_send_message.py
opensesame_plugins/titta/titta_send_message/titta_send_message_large.png
opensesame_plugins/titta/titta_start_recording/__init__.py
opensesame_plugins/titta/titta_start_recording/titta_start_recording.png
opensesame_plugins/titta/titta_start_recording/titta_start_recording.py
opensesame_plugins/titta/titta_start_recording/titta_start_recording_large.png
opensesame_plugins/titta/titta_stop_recording/__init__.py
opensesame_plugins/titta/titta_stop_recording/titta_stop_recording.png
opensesame_plugins/titta/titta_stop_recording/titta_stop_recording.py
opensesame_plugins/titta/titta_stop_recording/titta_stop_recording_large.png
opensesame_plugin_titta_eyetracking-6.1.0.dist-info/COPYING
opensesame_plugin_titta_eyetracking-6.1.0.dist-info/METADATA
opensesame_plugin_titta_eyetracking-6.1.0.dist-info/WHEEL
opensesame_plugin_titta_eyetracking-6.1.0.dist-info/RECORD
