Metadata-Version: 2.3
Name: opensesame-plugin-titta-eyetracking
Version: 6.1.0
Summary: Titta Eye Tracking plugin for OpenSesame
License: LICENSE.md
Author: Bob Rosbag
Author-email: debian@bobrosbag.nl
Requires-Python: >=3.8
Classifier: License :: Other/Proprietary License
Classifier: Programming Language :: Python :: 3
Classifier: Programming Language :: Python :: 3.8
Classifier: Programming Language :: Python :: 3.9
Classifier: Programming Language :: Python :: 3.10
Classifier: Programming Language :: Python :: 3.11
Classifier: Programming Language :: Python :: 3.12
Classifier: Programming Language :: Python :: 3.13
Requires-Dist: pandas
Requires-Dist: titta (>=2.1.0)
Requires-Dist: tittapy (>=1.0.0)
Project-URL: Homepage, https://github.com/dev-jam/opensesame-plugin-titta_eyetracking
Project-URL: Repository, https://github.com/dev-jam/opensesame-plugin-titta_eyetracking
